pyab/__init__.py
pyab/experiments/__init__.py
pyab/experiments/experiments.py
pyab/tests/__init__.py
pyab/tests/test_pyab.py
pyab/utils/__init__.py
pyab/utils/utils.py
pyAB-0.0.2.dist-info/LICENSE
pyAB-0.0.2.dist-info/METADATA
pyAB-0.0.2.dist-info/WHEEL
pyAB-0.0.2.dist-info/top_level.txt
pyAB-0.0.2.dist-info/RECORD
