Metadata-Version: 2.1
Name: pyAB
Version: 0.0.2
Summary: A/B Testing using Bayesian & Frequentist Statistics
Home-page: https://github.com/AdiVarma27/pyAB
Author: Aditya Varma Kalidindi
Author-email: kadityavarma27@gmail.com
License: UNKNOWN
Platform: UNKNOWN
Requires-Dist: numpy
Requires-Dist: matplotlib
Requires-Dist: seaborn
Requires-Dist: scipy
Requires-Dist: statsmodels
